pyedr/__init__.py
pyedr/pyedr.py
pyedr/tests/__init__.py
pyedr/tests/datafiles.py
pyedr/tests/test_edr.py
pyedr/tests/data/blocks.edr
pyedr/tests/data/blocks.xvg
pyedr/tests/data/blocks_units.p
pyedr/tests/data/cat_small.edr
pyedr/tests/data/cat_small.xvg
pyedr/tests/data/cat_small_units.p
pyedr/tests/data/double.edr
pyedr/tests/data/double.xvg
pyedr/tests/data/double_units.p
pyedr/tests/data/irregular.edr
pyedr/tests/data/irregular.xvg
pyedr/tests/data/irregular_units.p
pyedr-0.7.2.dist-info/LICENSE.txt
pyedr-0.7.2.dist-info/METADATA
pyedr-0.7.2.dist-info/WHEEL
pyedr-0.7.2.dist-info/pbr.json
pyedr-0.7.2.dist-info/top_level.txt
pyedr-0.7.2.dist-info/RECORD
