Metadata-Version: 2.1
Name: pyedr
Version: 0.7.2
Summary: Read and manipulate Gromacs energy files
Home-page: https://github.com/MDAnalysis/panedr
Author: Jonathan Barnoud
Author-email: jonathan@barnoud.net
License: LGPLv2+
Classifier: Development Status :: 4 - Beta
Classifier: Intended Audience :: Developers
Classifier: Topic :: Scientific/Engineering :: Bio-Informatics
Classifier: Topic :: Scientific/Engineering :: Chemistry
Classifier: Topic :: Scientific/Engineering :: Physics
Classifier: License :: OSI Approved :: GNU Lesser General Public License v2 or later (LGPLv2+)
Classifier: Programming Language :: Python :: 3.6
Classifier: Programming Language :: Python :: 3.7
Classifier: Programming Language :: Python :: 3.8
Classifier: Programming Language :: Python :: 3.9
Classifier: Programming Language :: Python :: 3.10
Classifier: Programming Language :: Python :: 3.11
Classifier: Operating System :: OS Independent
Requires-Python: >=3.6
License-File: LICENSE.txt
Requires-Dist: numpy >=1.19.0
Requires-Dist: pbr
Requires-Dist: tqdm
Requires-Dist: mda-xdrlib
Provides-Extra: test
Requires-Dist: pytest ; extra == 'test'
